Metadata-Version: 2.1
Name: inputidy
Version: 0.0.1
Summary: Python input interface
Home-page: https://github.com/Janus-Shiau/inputidy
Author: Jia-Yau Shiau
Author-email: jiayau_shiau@gmail.com
License: Apache Software License (Apache-2.0)
Requires-Python: >=3.7
License-File: LICENSE
